ghprai/__init__.py
ghprai/cli.py
ghprai/agents/__init__.py
ghprai/agents/ai_agent.py
ghprai/agents/dotnet_agent.py
ghprai/agents/github_agent.py
ghprai/core/__init__.py
ghprai/core/config.py
ghprai/core/dotnet_utils.py
ghprai/core/models.py
ghprai/core/utils.py
ghprai/server/__init__.py
ghprai/server/app.py
ghprai-0.2.0.dist-info/licenses/LICENSE
ghprai-0.2.0.dist-info/METADATA
ghprai-0.2.0.dist-info/WHEEL
ghprai-0.2.0.dist-info/entry_points.txt
ghprai-0.2.0.dist-info/top_level.txt
ghprai-0.2.0.dist-info/RECORD
