Metadata-Version: 2.4
Name: ghprai
Version: 0.2.0
Summary: AI-powered GitHub PR reviewer using Ollama for intelligent code analysis and test generation
Home-page: https://github.com/yourusername/ai-agent-pr-reviewer
Author: Your Name
Author-email: Raj Uppadhyay <uppadhyayraj@gmail.com>
License-Expression: MIT
Project-URL: Homepage, https://github.com/yourusername/ai-agent-pr-reviewer
Project-URL: Documentation, https://github.com/yourusername/ai-agent-pr-reviewer/blob/main/README.md
Project-URL: Repository, https://github.com/yourusername/ai-agent-pr-reviewer
Project-URL: Bug Tracker, https://github.com/yourusername/ai-agent-pr-reviewer/issues
Keywords: github,ai,code-review,testing,ollama,llm
Classifier: Development Status :: 3 - Alpha
Classifier: Intended Audience :: Developers
Classifier: Operating System :: OS Independent
Classifier: Programming Language :: Python :: 3
Classifier: Programming Language :: Python :: 3.9
Classifier: Programming Language :: Python :: 3.10
Classifier: Programming Language :: Python :: 3.11
Classifier: Programming Language :: Python :: 3.12
Classifier: Topic :: Software Development :: Testing
Classifier: Topic :: Software Development :: Version Control :: Git
Requires-Python: >=3.9
License-File: LICENSE
Requires-Dist: flask>=2.3.3
Requires-Dist: PyGithub>=1.59.1
Requires-Dist: requests>=2.31.0
Requires-Dist: python-dotenv>=1.0.0
Provides-Extra: dev
Requires-Dist: pytest>=7.4.0; extra == "dev"
Requires-Dist: pytest-asyncio>=0.23.5; extra == "dev"
Requires-Dist: black; extra == "dev"
Requires-Dist: flake8; extra == "dev"
Requires-Dist: mypy; extra == "dev"
Requires-Dist: pre-commit; extra == "dev"
Provides-Extra: server
Requires-Dist: gunicorn>=20.1.0; extra == "server"
Dynamic: author
Dynamic: home-page
Dynamic: license-file
Dynamic: requires-python
